flgo/__init__.py
flgo/algorithm/TiFL.py
flgo/algorithm/__init__.py
flgo/algorithm/afl.py
flgo/algorithm/asyncbase.py
flgo/algorithm/clustered_sampling.py
flgo/algorithm/decentralized.py
flgo/algorithm/ditto.py
flgo/algorithm/fedasync.py
flgo/algorithm/fedavg.py
flgo/algorithm/fedavgm.py
flgo/algorithm/fedbase.py
flgo/algorithm/fedbuff.py
flgo/algorithm/feddyn.py
flgo/algorithm/fedfa.py
flgo/algorithm/fedfv.py
flgo/algorithm/fedmf.py
flgo/algorithm/fedmgda.py
flgo/algorithm/fednova.py
flgo/algorithm/fedprox.py
flgo/algorithm/fedspeed.py
flgo/algorithm/hierarchical.py
flgo/algorithm/mifa.py
flgo/algorithm/moon.py
flgo/algorithm/powerofchoice.py
flgo/algorithm/qfedavg.py
flgo/algorithm/realbase.py
flgo/algorithm/scaffold.py
flgo/algorithm/sesorec.py
flgo/algorithm/standalone.py
flgo/algorithm/vflbase.py
flgo/algorithm/accelerate/__init__.py
flgo/algorithm/accelerate/fedavg.py
flgo/algorithm/accelerate/fedprox.py
flgo/algorithm/scale/__init__.py
flgo/benchmark/__init__.py
flgo/benchmark/base.py
flgo/benchmark/decorator.py
flgo/benchmark/partition.py
flgo/benchmark/adult_classification/__init__.py
flgo/benchmark/adult_classification/core.py
flgo/benchmark/adult_classification/model/__init__.py
flgo/benchmark/adult_classification/model/lr.py
flgo/benchmark/agnews_classification/__init__.py
flgo/benchmark/agnews_classification/config.py
flgo/benchmark/agnews_classification/core.py
flgo/benchmark/agnews_classification/model/default_model.py
flgo/benchmark/bankmarketing_classification/__init__.py
flgo/benchmark/bankmarketing_classification/core.py
flgo/benchmark/bankmarketing_classification/model/__init__.py
flgo/benchmark/bankmarketing_classification/model/lr.py
flgo/benchmark/ciao_recommendation/__init__.py
flgo/benchmark/ciao_recommendation/core.py
flgo/benchmark/ciao_recommendation/model/mf.py
flgo/benchmark/cifar100_classification/__init__.py
flgo/benchmark/cifar100_classification/config.py
flgo/benchmark/cifar100_classification/core.py
flgo-0.4.4.dist-info/licenses/LICENSE
flgo-0.4.4.dist-info/METADATA
flgo-0.4.4.dist-info/WHEEL
flgo-0.4.4.dist-info/top_level.txt
flgo-0.4.4.dist-info/RECORD
