Metadata-Version: 2.4
Name: flgo
Version: 0.4.4
Summary: A Research-oriented FL Platform. 
Author-email: Zheng Wang <zwang@stu.xmu.edu.cn>
Project-URL: Homepage, https://flgo-xmu.github.io
Project-URL: Bug Tracker, https://github.com/WwZzz/easyFL/issues
Classifier: Programming Language :: Python :: 3
Classifier: License :: OSI Approved :: MIT License
Classifier: Operating System :: OS Independent
Requires-Python: >=3.4
License-File: LICENSE
Requires-Dist: tqdm
Requires-Dist: torch
Requires-Dist: torchvision
Requires-Dist: scipy
Requires-Dist: matplotlib
Requires-Dist: prettytable
Requires-Dist: ujson
Requires-Dist: pynvml
Requires-Dist: pyyaml
Requires-Dist: networkx
Requires-Dist: requests
Requires-Dist: toolz
Dynamic: license-file
